simple_json_logging/__init__.py
simple_json_logging-2.0.0.dist-info/LICENSE
simple_json_logging-2.0.0.dist-info/METADATA
simple_json_logging-2.0.0.dist-info/WHEEL
simple_json_logging-2.0.0.dist-info/top_level.txt
simple_json_logging-2.0.0.dist-info/RECORD
