Metadata-Version: 2.1
Name: simple-json-logging
Version: 2.0.0
Summary: Library for structured logging via JSON document
Home-page: https://github.com/nevmerzhitsky/python-simple-json-logging
Author: Sergey Nevmerzhitsky
Author-email: sergey.nevmerzhitsky@gmail.com
License: MIT
Keywords: logging,json
Platform: UNKNOWN
Classifier: Development Status :: 4 - Beta
Classifier: Intended Audience :: Developers
Classifier: License :: OSI Approved :: MIT License
Classifier: Operating System :: OS Independent
Classifier: Topic :: Utilities
Classifier: Programming Language :: Python :: 3
Classifier: Programming Language :: Python :: 3.7
Requires-Python: ~=3.7
